[
    {
        "user": {
            "name": "익명",
            "mbti": "INFP"
        },
        "type": {
            "name": "질문",
            "imageName": "q.circle.fill",
        },
        "info": {
            "title": "테스트 질문1 제목",
            "context": "테스트 질문1의 본문 내용입니다. 테스트 질문1의 본문 내용입니다. 테스트 질문1의 본문 내용입니다.",
            "likeCount": 13,
            "commentCount": 15,
            "uploadDate": "dasd",
        }
    },
    {
        "user": {
            "name": "익명",
            "mbti": "INFP"
        },
        "type": {
            "name": "질문",
            "imageName": "q.circle.fill",
        },
        "info": {
            "title": "테스트 질문1 제목",
            "context": "테스트 질문1의 본문 내용입니다. 테스트 질문1의 본문 내용입니다. 테스트 질문1의 본문 내용입니다.",
            "likeCount": 13,
            "commentCount": 15,
            "uploadDate": "dasd",
        }
    },
    {
        "user": {
            "name": "익명",
            "mbti": "INFP"
        },
        "type": {
            "name": "질문",
            "imageName": "q.circle.fill",
        },
        "info": {
            "title": "테스트 질문1 제목",
            "context": "테스트 질문1의 본문 내용입니다. 테스트 질문1의 본문 내용입니다. 테스트 질문1의 본문 내용입니다.",
            "likeCount": 13,
            "commentCount": 15,
            "uploadDate": "dasd",
        }
    },
    {
        "user": {
            "name": "익명",
            "mbti": "INFP"
        },
        "type": {
            "name": "투표",
            "imageName": "q.circle.fill",
        },
        "info": {
            "title": "테스트 투표1 제목",
            "context": "테스트 투표1의 본문 내용입니다. 테스트 투표1의 본문 내용입니다. 테스트 투표1의 본문 내용입니다.",
            "likeCount": 13,
            "commentCount": 15,
            "uploadDate": "dasd",
        }
    },
    
]
